setup.py
distributions_Gauss/Binomialdistribution.py
distributions_Gauss/Gaussiandistribution.py
distributions_Gauss/Generaldistribution.py
distributions_Gauss/__init__.py
distributions_Gauss.egg-info/PKG-INFO
distributions_Gauss.egg-info/SOURCES.txt
distributions_Gauss.egg-info/dependency_links.txt
distributions_Gauss.egg-info/not-zip-safe
distributions_Gauss.egg-info/top_level.txt