Metadata-Version: 1.0
Name: distributions-Gauss
Version: 0.1
Summary: Gaussian distributions
Home-page: UNKNOWN
Author: LOGESWARAN SIVAKUMAR
Author-email: UNKNOWN
License: UNKNOWN
Platform: UNKNOWN
